edgehog/__init__.py
edgehog/add_ons.py
edgehog/characterize_species_tree.py
edgehog/check_args.py
edgehog/edgehog.py
edgehog/hdf5.py
edgehog/infer_ancestral_synteny_graphs.py
edgehog/init_extant_synteny_graphs.py
edgehog/process_hogs.py
edgehog/read_gff.py
edgehog/write_output.py
edgehog-0.1.9.dist-info/LICENSE.txt
edgehog-0.1.9.dist-info/METADATA
edgehog-0.1.9.dist-info/WHEEL
edgehog-0.1.9.dist-info/entry_points.txt
edgehog-0.1.9.dist-info/RECORD
