Metadata-Version: 2.3
Name: edgehog
Version: 0.1.9
Summary: Infering ancestral synteny with hierarchical orthologous groups
License: MIT
Keywords: bioinformatics,synteny,ancestral gene order
Author: Charles Bernard
Author-email: charles.bernard@unil.ch
Requires-Python: >=3.9,<3.13
Classifier: Topic :: Scientific/Engineering :: Bio-Informatics
Classifier: Programming Language :: Python :: 3
Provides-Extra: oma
Requires-Dist: ete3 (>=3.1.3,<4)
Requires-Dist: networkx (>=2.8,<4)
Requires-Dist: numpy (>=1.23.0,<3)
Requires-Dist: pandas (>1.3.0,<3)
Requires-Dist: pyham (>=1.2,<2)
Requires-Dist: pyoma (>=0.13.3,<1) ; extra == "oma"
Requires-Dist: tables (<=3.10.0) ; (python_version < "3.11") and (extra == "oma")
Requires-Dist: tables (>=3.10) ; (python_version >= "3.11") and (extra == "oma")
